CongLingdaoYiTonyFanyiBan/README.md
CongLingdaoYiTonyFanyiBan/__init__.py
CongLingdaoYiTonyFanyiBan/__main__.py
CongLingdaoYiTonyFanyiBan/file.epub
CongLingdaoYiTonyFanyiBan/index.html
CongLingdaoYiTonyFanyiBan/css/__init__.py
CongLingdaoYiTonyFanyiBan/css/annotations.css
CongLingdaoYiTonyFanyiBan/css/main.css
CongLingdaoYiTonyFanyiBan/css/normalize.css
CongLingdaoYiTonyFanyiBan/css/popup.css
CongLingdaoYiTonyFanyiBan/font/__init__.py
CongLingdaoYiTonyFanyiBan/font/fontello.eot
CongLingdaoYiTonyFanyiBan/font/fontello.svg
CongLingdaoYiTonyFanyiBan/font/fontello.ttf
CongLingdaoYiTonyFanyiBan/font/fontello.woff
CongLingdaoYiTonyFanyiBan/img/__init__.py
CongLingdaoYiTonyFanyiBan/img/annotator-glyph-sprite.png
CongLingdaoYiTonyFanyiBan/img/annotator-icon-sprite.png
CongLingdaoYiTonyFanyiBan/img/apple-touch-icon.png
CongLingdaoYiTonyFanyiBan/img/cancelfullscreen.png
CongLingdaoYiTonyFanyiBan/img/close.png
CongLingdaoYiTonyFanyiBan/img/fullscreen.png
CongLingdaoYiTonyFanyiBan/img/loader.gif
CongLingdaoYiTonyFanyiBan/img/menu-icon.png
CongLingdaoYiTonyFanyiBan/img/save.png
CongLingdaoYiTonyFanyiBan/img/saved.png
CongLingdaoYiTonyFanyiBan/img/settings-s.png
CongLingdaoYiTonyFanyiBan/img/settings.png
CongLingdaoYiTonyFanyiBan/img/star.png
CongLingdaoYiTonyFanyiBan/js/__init__.py
CongLingdaoYiTonyFanyiBan/js/epub.js
CongLingdaoYiTonyFanyiBan/js/epub.min.js
CongLingdaoYiTonyFanyiBan/js/epub.min.map
CongLingdaoYiTonyFanyiBan/js/hooks.min.js
CongLingdaoYiTonyFanyiBan/js/hooks.min.map
CongLingdaoYiTonyFanyiBan/js/reader.js
CongLingdaoYiTonyFanyiBan/js/reader.js.map
CongLingdaoYiTonyFanyiBan/js/reader.min.js
CongLingdaoYiTonyFanyiBan/js/reader.min.map
CongLingdaoYiTonyFanyiBan/js/hooks/__init__.py
CongLingdaoYiTonyFanyiBan/js/hooks/extensions/__init__.py
CongLingdaoYiTonyFanyiBan/js/hooks/extensions/highlight.js
CongLingdaoYiTonyFanyiBan/js/libs/__init__.py
CongLingdaoYiTonyFanyiBan/js/libs/jquery.min.js
CongLingdaoYiTonyFanyiBan/js/libs/localforage.min.js
cong_lingdao_yi_tony_fanyi_ban-2024.3.3.0.dist-info/METADATA
cong_lingdao_yi_tony_fanyi_ban-2024.3.3.0.dist-info/WHEEL
cong_lingdao_yi_tony_fanyi_ban-2024.3.3.0.dist-info/entry_points.txt
cong_lingdao_yi_tony_fanyi_ban-2024.3.3.0.dist-info/top_level.txt
cong_lingdao_yi_tony_fanyi_ban-2024.3.3.0.dist-info/RECORD
